colour.py
colour-0.1.4.dist-info/DESCRIPTION.rst
colour-0.1.4.dist-info/LICENSE.txt
colour-0.1.4.dist-info/METADATA
colour-0.1.4.dist-info/RECORD
colour-0.1.4.dist-info/WHEEL
colour-0.1.4.dist-info/metadata.json
colour-0.1.4.dist-info/top_level.txt
