Metadata-Version: 1.1
Name: colour
Version: 0.1.4
Summary: converts and manipulates various color representation (HSL, RVB, web, X11, ...)
Home-page: http://github.com/vaab/colour
Author: Valentin LAB
Author-email: valentin.lab@kalysto.org
License: BSD 3-Clause License
Platform: UNKNOWN
Classifier: Programming Language :: Python
Classifier: Topic :: Software Development :: Libraries :: Python Modules
Classifier: Development Status :: 3 - Alpha
Classifier: License :: OSI Approved :: BSD License
Classifier: Intended Audience :: Developers
Classifier: Programming Language :: Python :: 2
Classifier: Programming Language :: Python :: 2.7
Classifier: Programming Language :: Python :: 3
Classifier: Programming Language :: Python :: 3.3
Classifier: Programming Language :: Python :: 3.4
Classifier: Programming Language :: Python :: 3.5
Classifier: Programming Language :: Python :: 3.6
